Metadata-Version: 1.0
Name: hazelib
Version: 0.0.14
Summary: My utility package.
Home-page: http://github.com/hazelpy/hazelib
Author: Hazelpy
Author-email: hazelpytv@gmail.com
License: MIT
Platform: UNKNOWN
